{
  "2": "გიორგი კაკაბაძე",
  "3": "გიორგი ინასარიძე",
  "4": "გიორგი ნიკოლაიშვილი",
  "5": "ირაკლი მდივნიშვილი",
  "6": "ნიკალა გოგოლაძე",
  "7": "ნიკოლოზ ნიკოლაიშვილი",
  "8": "თემუკა მახარაძე",
  "9": "ეკა ვადაჭკორია",
  "10": "გია ბერიძე & მარიკა გელაშვილი",
  "11": "ირაკლი კაკაბაძე",
  "12": "მარი გელაშვილი & სანდრო კერესელიძე",
  "13": "მარიამ არველაძე & ვახო ჭანკვეტაძე",
  "14": "მარიკა სულაბერიძე",
  "15": "ნინო ფირცხალავა",
  "16": "ნუცა ჟორჟოლაძე",
  "17": "თემიკო ჟორჟოლაძე & ქეთი ბერიძე",
  "18": "მარიამ გიგინეიშვილი & ლევან მჟავია",
  "19": "მაშო ჯმუხაძე & აკო მაჭავარიანი",
  "20": "ანა გვიმრაძე & ლევან სხვითარიძე",
  "21": "ელენე კაჭარავა & ლევან გომშიაშვილი",
  "22": "ნინი ახვლედიანი",
  "23": "თათია კუკულავა & სანდრო შათირიშვილი",
  "24": "ალექსანდრე ჩიქობავა",
  "25": "ანა ქაჯაია",
  "26": "არტემ მარტიროსიანი",
  "27": "ქეტი ჯანგველაძე & ანზორ გოგიბერიძე",
  "28": "მაკო ქერქაძე",
  "29": "ვიქტორია არუთინოვა",
  "30": "დავით კაკაბაძე & თუთა თუთარაული",
  "31": "გოგა სულაძე",
  "32": "გია ნიკოლაიშვილი",
  "33": "ლალი კანკავა",
  "34": "ლევან ნიკოლაიშვილი",
  "35": "ნანა კასრელიშვილი",
  "36": "ნათია სულაძე",
  "37": "ნიკო სულაძე",
  "38": "პეტო კანკავა & თამუნა ქოჩორაძე",
  "39": "სანდრო სულაძე",
  "40": "თეიმურაზ ნიკოლაიშვილი, ელენე ბერიძე & ოსპიკო",
  "41": "თიკო თევზაძე",
  "42": "ხათუნა ჯანგველაძე",
  "43": "ნატო ბერიძე",
  "44": "ქეთი ლეჟავა",
  "45": "დაჩი ქარსაულიძე",
  "46": "სანდრო გეგუჩაძე & ეკა ხეთერელი",
  "47": "მარიამ თაყნიაშვილი & ილია კასინი",
  "48": "ინეზა სტურუა",
  "49": "ჯონი თაყნიაშვილი",
  "50": "ზურა გეგუჩაძე & მაკა გეგუჩაძე",
  "51": "მამუკა & მაკა",
  "52": "ნანა მაისურაძე",
  "53": "საბა გეგუჩაძე",
  "54": "თაკო ჯღარკავა",
  "55": "თამარ ქარსაულიძე",
  "56": "თამარა გამყრელიძე",
  "57": "თეკლა ქარსაულიძე",
  "58": "თეონა ჩიკვაიძე",
  "59": "თორნიკე ჩიკვაიძე & ქეტი ჩიკვაიძე",
  "60": "შოთა ჩიკვაიძე & ია ჩიკვაიძე",
  "61": "თინათინ ჯანდიერი",
  "62": "თომა რუსიტაშვილი",
  "63": "ზაზა ქარსაულიძე & მარიკა ფირანიშვილი",
  "64": "არჩილ ქურციკიძე & სალომე ყიფშიძე",
  "65": "დავით ნადირაძე",
  "66": "გიორგი ღავთაძე & ნუცა უთმელიძე",
  "67": "გუგა & ანასტასია",
  "68": "ირინა მინდელი",
  "69": "ლუკა & ნანუცა",
  "70": "ნატო წერეთელი კახას ასული",
  "71": "თეონა ჩალიგავა & საბა თვარაძე",
  "72": "გოგლიკო ჭოხონელიძე",
  "73": "ივანე ძოძუაშვილი",
  "74": "სოფო მხეიძე",
  "75": "ანასტასია ლეჟავა",
  "76": "ეკა დვალიშვილი",
  "77": "იანა ძაგნიძე",
  "78": "ლაშა ლეჟავა",
  "79": "ლიზა ლეჟავა",
  "80": "ლუკა ლეჟავა",
  "81": "მადონა თოდუა",
  "82": "მარიამ & დანიელ",
  "83": "მარიამ ლეჟავა",
  "84": "მარიშკა ლეჟავა",
  "85": "პაატა ლეჟავა",
  "86": "ტომა მეუნარგია",
  "87": "ელიზა ჯოჯიშვილი",
  "88": "ქეთინო მაისურაძე",
  "89": "ლაზარე გიუნაშვილი",
  "90": "საბა საბაშვილი",
  "91": "დათა კალანდაძე",
  "92": "თორნიკე გელოვანი",
  "93": "ნანჩო აბულაძე",
  "94": "თათუკა კაკაბაძე",
  "95": "ნინო ლასხიშვილი"
}